errorwatch/__init__.py
errorwatch-0.2.0.dist-info/METADATA
errorwatch-0.2.0.dist-info/WHEEL
errorwatch-0.2.0.dist-info/licenses/LICENSE
errorwatch-0.2.0.dist-info/RECORD
