Metadata-Version: 2.4
Name: errorwatch
Version: 0.2.0
Summary: Intercept Python exceptions and send them to a server
Project-URL: Homepage, https://github.com/rodmena-limited/errorwatch
Project-URL: Repository, https://github.com/rodmena-limited/errorwatch
Project-URL: Issues, https://github.com/rodmena-limited/errorwatch/issues
Author: Farshid Ashouri
License-Expression: Apache-2.0
License-File: LICENSE
Keywords: error-tracking,exceptions,logging,monitoring,sentry-alternative
Classifier: Development Status :: 3 - Alpha
Classifier: Intended Audience :: Developers
Classifier: License :: OSI Approved :: Apache Software License
Classifier: Programming Language :: Python :: 3
Classifier: Programming Language :: Python :: 3.8
Classifier: Programming Language :: Python :: 3.9
Classifier: Programming Language :: Python :: 3.10
Classifier: Programming Language :: Python :: 3.11
Classifier: Programming Language :: Python :: 3.12
Requires-Python: >=3.8
Requires-Dist: requests>=2.20.0
